<?xml version="1.0" encoding="utf-8"?><gestures><gesture name="FASHION_19"><point x="-133.8181" y="3.818604" /><point x="-132.7793" y="-9.572998" /><point x="-128.3832" y="-21.16705" /><point x="-123.6563" y="-32.51331" /><point x="-120.2434" y="-45.03955" /><point x="-116.648" y="-57.43787" /><point x="-114.0367" y="-70.46857" /><point x="-112.9891" y="-83.83765" /><point x="-110.8699" y="-96.72357" /><point x="-108.2088" y="-109.6774" /><point x="-100.6206" y="-115.9603" /><point x="-92.65623" y="-120.4845" /><point x="-84.08705" y="-121.1396" /><point x="-75.49609" y="-121.3112" /><point x="-66.93704" y="-122.5328" /><point x="-58.33145" y="-122.2225" /><point x="-49.9024" y="-123.9303" /><point x="-41.36638" y="-125.072" /><point x="-32.88431" y="-127.3403" /><point x="-24.31366" y="-126.4384" /><point x="-16.50128" y="-122.154" /><point x="-10.55429" y="-112.2601" /><point x="-4.962341" y="-101.8738" /><point x="0.3968201" y="-91.16455" /><point x="5.805527" y="-80.51959" /><point x="11.32536" y="-70.01862" /><point x="17.16377" y="-59.97052" /><point x="23.24448" y="-50.29596" /><point x="29.65128" y="-41.15643" /><point x="35.07785" y="-30.54822" /><point x="40.90009" y="-20.48126" /><point x="46.30551" y="-9.851318" /><point x="52.1131" y="0.2321167" /><point x="58.13791" y="9.996399" /><point x="64.62393" y="18.99365" /><point x="69.59064" y="30.14551" /><point x="75.13708" y="40.59503" /><point x="81.62238" y="49.49194" /><point x="87.61667" y="59.29828" /><point x="93.56369" y="69.19208" /><point x="98.67035" y="80.14105" /><point x="104.734" y="89.35034" /><point x="110.39" y="99.29736" /><point x="116.1819" y="109.0591" /><point x="109.6573" y="116.5505" /><point x="101.484" y="120.4468" /><point x="93.07919" y="122.6597" /><point x="84.4736" y="122.3493" /><point x="75.86801" y="122.0389" /><point x="67.64413" y="118.9216" /><point x="59.35815" y="115.3702" /><point x="51.03677" y="111.9507" /><point x="42.86783" y="107.6652" /><point x="34.90796" y="102.5477" /><point x="27.02348" y="97.05902" /><point x="19.25951" y="91.22552" /><point x="11.06616" y="87.04944" /><point x="3.240662" y="81.37286" /><point x="-4.36911" y="74.97662" /><point x="-12.40601" y="70.15088" /><point x="-20.0094" y="63.99744" /><point x="-27.56812" y="57.73218" /><point x="-35.29535" y="52.16992" /><point x="-43.32361" y="47.32159" /></gesture><gesture name="FASHION_19"><point x="-109.9527" y="1.04715" /><point x="-107.4229" y="9.378754" /><point x="-109.3382" y="17.66556" /><point x="-113.0548" y="25.76379" /><point x="-114.2166" y="34.18341" /><point x="-115.061" y="42.60678" /><point x="-115.6111" y="51.04361" /><point x="-113.2937" y="59.37805" /><point x="-114.293" y="67.80038" /><point x="-115.285" y="76.17166" /><point x="-112.5286" y="84.49448" /><point x="-109.7721" y="92.81723" /><point x="-107.0156" y="101.14" /><point x="-104.2592" y="109.4628" /><point x="-101.5027" y="117.7856" /><point x="-92.69992" y="124.6523" /><point x="-82.26663" y="129.337" /><point x="-75.45508" y="122.4412" /><point x="-70.19565" y="114.4758" /><point x="-61.97607" y="108.2581" /><point x="-52.733" y="101.5756" /><point x="-47.50546" y="93.65552" /><point x="-41.06097" y="85.99805" /><point x="-32.0903" y="79.00397" /><point x="-24.11078" y="71.68445" /><point x="-14.77634" y="64.81976" /><point x="-4.163544" y="58.48645" /><point x="6.185089" y="52.05325" /><point x="14.18002" y="44.72974" /><point x="25.08276" y="38.57065" /><point x="35.19254" y="32.04944" /><point x="45.23874" y="25.49173" /><point x="57.54703" y="20.12207" /><point x="69.16125" y="14.297" /><point x="80.77554" y="8.471954" /><point x="93.37973" y="3.267914" /><point x="104.846" y="-2.488647" /><point x="115.2967" y="-8.842072" /><point x="127.8389" y="-13.9335" /><point x="134.3889" y="-21.43399" /><point x="134.1351" y="-29.77246" /><point x="131.3786" y="-38.09525" /><point x="128.6222" y="-46.418" /><point x="125.8657" y="-54.74078" /><point x="123.1092" y="-63.06357" /><point x="120.5487" y="-71.3978" /><point x="119.7728" y="-79.83646" /><point x="117.3097" y="-88.17642" /><point x="119.6413" y="-96.34067" /><point x="116.8849" y="-104.6634" /><point x="103.5537" y="-109.249" /><point x="88.19241" y="-111.672" /><point x="72.81656" y="-114.0648" /><point x="57.06235" y="-115.568" /><point x="41.43161" y="-117.2177" /><point x="25.65686" y="-117.5471" /><point x="10.43689" y="-119.1646" /><point x="-5.577362" y="-119.5444" /><point x="-21.46323" y="-120.663" /><point x="-36.72879" y="-118.6265" /><point x="-46.71359" y="-112.2464" /><point x="-52.8855" y="-104.4522" /><point x="-59.02692" y="-96.65048" /><point x="-61.496" y="-88.30911" /></gesture><gesture name="FASHION_19"><point x="-130.5628" y="0.2374878" /><point x="-130.2934" y="-12.83954" /><point x="-128.7695" y="-25.68951" /><point x="-125.2217" y="-37.67102" /><point x="-120.6577" y="-48.76117" /><point x="-115.4746" y="-59.3111" /><point x="-111.5671" y="-71.03906" /><point x="-107.9671" y="-82.97998" /><point x="-104.3037" y="-94.87701" /><point x="-99.81267" y="-106.0661" /><point x="-96.20769" y="-117.8425" /><point x="-96.74084" y="-113.2001" /><point x="-98.02437" y="-100.2836" /><point x="-98.0163" y="-87.17743" /><point x="-91.95302" y="-78.82129" /><point x="-83.62854" y="-74.77887" /><point x="-75.01662" y="-73.05518" /><point x="-66.26308" y="-73.06726" /><point x="-57.50951" y="-73.07941" /><point x="-48.86934" y="-74.78986" /><point x="-42.02582" y="-82.47382" /><point x="-35.42264" y="-90.60602" /><point x="-30.77461" y="-101.626" /><point x="-25.29071" y="-111.0571" /><point x="-19.53987" y="-115.4764" /><point x="-16.44456" y="-103.4009" /><point x="-12.52267" y="-91.68372" /><point x="-7.951202" y="-80.66901" /><point x="-2.343491" y="-70.64545" /><point x="2.134979" y="-59.49951" /><point x="7.970642" y="-49.75763" /><point x="13.8096" y="-40.02014" /><point x="19.16824" y="-29.73218" /><point x="24.70871" y="-19.66791" /><point x="31.31104" y="-11.09094" /><point x="38.25806" y="-3.119385" /><point x="44.77481" y="5.32135" /><point x="51.10565" y="14.20007" /><point x="58.44766" y="21.2959" /><point x="65.53375" y="28.97491" /><point x="72.54144" y="36.82898" /><point x="80.31662" y="42.26312" /><point x="87.63861" y="49.16382" /><point x="96.05969" y="52.7077" /><point x="103.802" y="58.5614" /><point x="109.0832" y="68.76605" /><point x="113.9045" y="79.68475" /><point x="118.326" y="90.90796" /><point x="119.4372" y="103.8093" /><point x="118.2847" y="116.3911" /><point x="111.7847" y="124.8354" /><point x="103.9011" y="130.0756" /><point x="95.22485" y="131.0216" /><point x="86.56238" y="132.1333" /><point x="77.80884" y="132.1454" /><point x="69.0553" y="132.1575" /><point x="60.49899" y="130.1195" /><point x="52.10382" y="126.4078" /><point x="43.70868" y="122.696" /><point x="35.31348" y="118.9843" /><point x="27.11838" y="114.6315" /><point x="20.50912" y="106.1298" /><point x="12.28067" y="101.8062" /><point x="6.687973" y="93.60181" /></gesture></gestures>