<?xml version="1.0" encoding="utf-8"?><gestures><gesture name="FOOD_50"><point x="-123.8938" y="2.107422" /><point x="-122.8062" y="-106.3242" /><point x="-119.3388" y="-126.2168" /><point x="-115.2613" y="-123.4121" /><point x="-111.1837" y="-120.6094" /><point x="-107.1255" y="-130.2451" /><point x="-103.0717" y="-142.6631" /><point x="-99.03589" y="-146.6084" /><point x="-95.06291" y="-121.1475" /><point x="-91.0899" y="-95.68945" /><point x="-87.11691" y="-70.23047" /><point x="-83.14391" y="-44.77344" /><point x="-79.17093" y="-19.3125" /><point x="-75.15379" y="-2.507813" /><point x="-71.08035" y="3.254883" /><point x="-67.00691" y="9.017578" /><point x="-62.93347" y="14.78125" /><point x="-58.86003" y="20.54102" /><point x="-54.78661" y="26.30371" /><point x="-50.71318" y="32.06543" /><point x="-46.63974" y="37.82715" /><point x="-42.5663" y="43.58789" /><point x="-38.48993" y="45.60352" /><point x="-34.41129" y="44.65918" /><point x="-30.39395" y="27.02734" /><point x="-26.39148" y="5.367188" /><point x="-22.38046" y="-14.11523" /><point x="-18.30261" y="-16.53906" /><point x="-14.22476" y="-18.96484" /><point x="-10.14966" y="-23.42773" /><point x="-6.076324" y="-29.25977" /><point x="-2.003052" y="-35.08984" /><point x="2.060944" y="-31.1875" /><point x="6.117401" y="-19.42285" /><point x="10.17383" y="-7.65918" /><point x="14.24362" y="-4.742188" /><point x="18.32147" y="-7.166016" /><point x="22.39575" y="-7.753906" /><point x="26.44119" y="6.609375" /><point x="30.48657" y="20.97266" /><point x="34.53201" y="35.33398" /><point x="38.59338" y="45.3252" /><point x="42.66147" y="53.47656" /><point x="46.72299" y="55.84668" /><point x="50.76465" y="40.70605" /><point x="54.81247" y="36.70898" /><point x="58.8689" y="48.47363" /><point x="62.9364" y="56.80859" /><point x="66.90564" y="80.72168" /><point x="70.8674" y="98.2334" /><point x="74.90903" y="83.09277" /><point x="78.95728" y="79.8623" /><point x="83.01373" y="91.62695" /><point x="87.07016" y="103.3916" /><point x="91.05148" y="92.68457" /><point x="94.96149" y="60.6543" /><point x="98.90683" y="39.19434" /><point x="102.9633" y="50.95898" /><point x="106.9778" y="36.76563" /><point x="110.9926" y="18.44238" /><point x="115.0712" y="17.49805" /><point x="118.803" y="-11.11328" /><point x="122.1751" y="-59.71191" /><point x="126.1062" y="-29.71289" /></gesture><gesture name="FOOD_50"><point x="-124.9639" y="-0.04589844" /><point x="-121.0149" y="16.14648" /><point x="-117.066" y="32.33984" /><point x="-113.1147" y="48.06641" /><point x="-109.1442" y="59.8877" /><point x="-105.1702" y="68.92285" /><point x="-101.1789" y="64.30273" /><point x="-97.1924" y="57.7334" /><point x="-93.21239" y="48.47461" /><point x="-89.23241" y="39.21582" /><point x="-85.24812" y="31.72266" /><point x="-81.25688" y="27.10254" /><point x="-77.29955" y="13.98145" /><point x="-73.36201" y="-4.095703" /><point x="-69.41177" y="4.666016" /><point x="-65.4584" y="20.06348" /><point x="-61.50031" y="34.28809" /><point x="-57.51511" y="41.76465" /><point x="-53.53508" y="50.94238" /><point x="-49.55745" y="60.89844" /><point x="-45.59282" y="47.99609" /><point x="-41.62834" y="34.80078" /><point x="-37.64935" y="25.28125" /><point x="-33.66431" y="21.5332" /><point x="-29.67175" y="25.13477" /><point x="-25.67731" y="26.8916" /><point x="-21.68286" y="28.64844" /><point x="-17.79495" y="52.96777" /><point x="-13.90543" y="77.20508" /><point x="-9.934937" y="89.02734" /><point x="-5.973541" y="96.71094" /><point x="-2.082489" y="72.47266" /><point x="1.859894" y="58.74902" /><point x="5.852966" y="55.41602" /><point x="9.845978" y="52.08398" /><point x="13.83307" y="57.00293" /><point x="17.80106" y="56.34473" /><point x="21.72925" y="36.8623" /><point x="25.65744" y="17.38184" /><point x="29.64792" y="15.13086" /><point x="33.64273" y="14.07324" /><point x="37.63498" y="17.87305" /><point x="41.59848" y="7.669922" /><point x="45.5513" y="-7.831055" /><point x="49.50952" y="-21.7998" /><point x="53.50076" y="-26.42188" /><point x="57.4834" y="-33.9834" /><point x="61.45258" y="-46.11816" /><point x="65.42178" y="-58.25293" /><point x="69.40427" y="-61.02441" /><point x="73.39642" y="-56.99219" /><point x="77.38696" y="-54.67383" /><point x="81.36694" y="-63.93164" /><point x="85.34695" y="-73.18945" /><point x="89.33951" y="-75.4834" /><point x="93.33429" y="-76.54102" /><point x="97.27127" y="-93.59082" /><point x="101.1995" y="-113.0713" /><point x="105.158" y="-125.8027" /><point x="109.1466" y="-131.8301" /><point x="113.1352" y="-137.8564" /><point x="117.0883" y="-153.2891" /><point x="121.0585" y="-150.9971" /><point x="125.0361" y="-141.0439" /></gesture><gesture name="FOOD_50"><point x="-124.5205" y="0.7861328" /><point x="-121.9626" y="-57.80957" /><point x="-118.3906" y="-79.22852" /><point x="-114.3612" y="-83.87793" /><point x="-110.3318" y="-88.53027" /><point x="-106.3024" y="-90.41797" /><point x="-102.2729" y="-85.81836" /><point x="-98.24232" y="-83.50977" /><point x="-94.20909" y="-86.76953" /><point x="-90.17586" y="-90.02832" /><point x="-86.15144" y="-88.22363" /><point x="-82.13646" y="-80.35645" /><point x="-78.11479" y="-73.76953" /><point x="-74.09309" y="-67.18457" /><point x="-70.09488" y="-56.74609" /><point x="-66.0795" y="-50.19727" /><point x="-62.04405" y="-48.12012" /><point x="-58.01544" y="-51.48926" /><point x="-54.01137" y="-49.5498" /><point x="-50.04062" y="-35.88672" /><point x="-46.04156" y="-28.63184" /><point x="-42.0051" y="-29.8457" /><point x="-37.97824" y="-35.02051" /><point x="-33.96912" y="-31.23535" /><point x="-29.97299" y="-22.86816" /><point x="-25.98624" y="-34.77734" /><point x="-21.97949" y="-38.98242" /><point x="-17.94998" y="-34.38379" /><point x="-13.92789" y="-28.13574" /><point x="-9.913757" y="-23.37207" /><point x="-5.896606" y="-30.86914" /><point x="-1.880859" y="-32.64941" /><point x="2.130463" y="-24.16113" /><point x="6.127625" y="-13.54883" /><point x="10.14673" y="-12.33496" /><point x="14.17804" y="-16.35156" /><point x="18.21225" y="-18.78906" /><point x="22.24814" y="-19.78418" /><point x="26.26144" y="-11.59473" /><point x="30.28445" y="-14.23438" /><point x="34.29669" y="-12.22559" /><point x="38.29385" y="-1.612305" /><point x="42.30701" y="6.600586" /><point x="46.19775" y="25.7373" /><point x="50.14322" y="38.84766" /><point x="54.17276" y="43.44531" /><point x="58.20538" y="46.71973" /><point x="62.24084" y="48.79785" /><point x="66.2276" y="59.59766" /><point x="70.19836" y="73.25977" /><point x="74.04114" y="56.28516" /><point x="77.95795" y="51.66016" /><point x="81.9538" y="62.43359" /><point x="85.93671" y="74.78613" /><point x="89.93692" y="84.26074" /><point x="93.96646" y="88.85938" /><point x="97.93054" y="100.085" /><point x="101.7803" y="122.8818" /><point x="105.718" y="138.7842" /><point x="109.7009" y="151.1377" /><point x="113.7123" y="159.582" /><point x="117.583" y="144.5439" /><point x="121.4824" y="136.6094" /><point x="125.4795" y="147.2227" /></gesture></gestures>