<?xml version="1.0" encoding="utf-8"?><gestures><gesture name="FOOD_42"><point x="-135.6068" y="-4.022339" /><point x="-124.0315" y="-3.479797" /><point x="-113.4641" y="1.809814" /><point x="-102.4102" y="6.046448" /><point x="-91.43253" y="10.47015" /><point x="-80.62558" y="15.25781" /><point x="-70.11478" y="20.66992" /><point x="-58.94653" y="24.59802" /><point x="-47.83167" y="28.61749" /><point x="-38.3681" y="35.65601" /><point x="-28.23175" y="41.42944" /><point x="-16.95972" y="45.06738" /><point x="-6.605225" y="50.599" /><point x="3.467468" y="56.75104" /><point x="13.85791" y="62.34344" /><point x="23.086" y="69.67847" /><point x="33.20673" y="75.67517" /><point x="44.30463" y="79.76196" /><point x="53.71985" y="86.76764" /><point x="63.59741" y="93.12891" /><point x="74.10815" y="98.54083" /><point x="84.40863" y="104.3001" /><point x="94.29602" y="110.7413" /><point x="104.8068" y="116.1533" /><point x="114.3932" y="122.8263" /><point x="112.2949" y="111.7121" /><point x="105.1235" y="102.4539" /><point x="99.61237" y="92.11743" /><point x="94.10126" y="81.78088" /><point x="88.18835" y="71.66162" /><point x="82.21777" y="61.57587" /><point x="76.03461" y="51.6142" /><point x="71.46136" y="40.93402" /><point x="67.37433" y="30.02167" /><point x="61.76923" y="19.73547" /><point x="56.41315" y="9.320313" /><point x="51.05707" y="-1.094849" /><point x="47.34375" y="-12.16669" /><point x="43.80066" y="-23.30646" /><point x="40.25757" y="-34.44629" /><point x="36.71448" y="-45.58618" /><point x="33.17151" y="-56.72601" /><point x="29.62842" y="-67.86591" /><point x="26.08533" y="-79.0058" /><point x="22.5423" y="-90.14557" /><point x="18.99927" y="-101.2854" /><point x="15.45618" y="-112.4253" /><point x="11.56201" y="-123.2766" /><point x="0.7581787" y="-127.1737" /><point x="-10.9245" y="-125.4004" /><point x="-22.24597" y="-121.9141" /><point x="-33.56744" y="-118.4279" /><point x="-44.59583" y="-114.4055" /><point x="-53.73022" y="-106.9632" /><point x="-62.27188" y="-98.86316" /><point x="-69.53564" y="-89.67365" /><point x="-77.2532" y="-80.82062" /><point x="-84.47644" y="-71.57788" /><point x="-92.57483" y="-63.09979" /><point x="-97.185" y="-52.50922" /><point x="-101.1435" y="-41.50549" /><point x="-106.7083" y="-31.23212" /><point x="-112.5227" y="-21.3075" /><point x="-115.8547" y="-10.1048" /></gesture><gesture name="FOOD_42"><point x="-139.2487" y="-0.8610229" /><point x="-135.009" y="-11.87646" /><point x="-126.5388" y="-20.78204" /><point x="-118.1968" y="-29.7832" /><point x="-111.0155" y="-39.64917" /><point x="-101.918" y="-47.97223" /><point x="-93.26532" y="-56.81085" /><point x="-84.6622" y="-65.72992" /><point x="-74.73834" y="-73.43628" /><point x="-65.70087" y="-81.9834" /><point x="-55.85486" y="-89.82062" /><point x="-44.64267" y="-95.8374" /><point x="-34.17041" y="-102.468" /><point x="-21.96869" y="-106.6758" /><point x="-10.23865" y="-112.0804" /><point x="2.295593" y="-115.5281" /><point x="14.47571" y="-119.8862" /><point x="27.39478" y="-122.3446" /><point x="40.17383" y="-123.3108" /><point x="46.67023" y="-114.6262" /><point x="49.43341" y="-103.132" /><point x="52.19659" y="-91.63776" /><point x="54.95978" y="-80.14349" /><point x="57.72296" y="-68.64935" /><point x="60.48615" y="-57.15509" /><point x="63.24933" y="-45.66083" /><point x="66.01245" y="-34.16669" /><point x="68.7757" y="-22.67242" /><point x="71.53882" y="-11.17822" /><point x="74.302" y="0.31604" /><point x="77.55591" y="11.67841" /><point x="81.98242" y="22.72571" /><point x="84.74567" y="34.21991" /><point x="87.50879" y="45.71411" /><point x="90.27197" y="57.20831" /><point x="93.03516" y="68.70258" /><point x="95.79834" y="80.19678" /><point x="98.56152" y="91.69104" /><point x="101.3247" y="103.1852" /><point x="104.0879" y="114.6795" /><point x="105.2753" y="126.0566" /><point x="96.70923" y="126.6892" /><point x="84.57703" y="122.1002" /><point x="72.59924" y="117.1649" /><point x="61.5224" y="110.8524" /><point x="51.01678" y="103.7253" /><point x="39.92865" y="97.33496" /><point x="28.83966" y="90.94568" /><point x="18.69513" y="83.44086" /><point x="8.574646" y="75.90778" /><point x="-2.152405" y="69.07678" /><point x="-12.66785" y="61.98761" /><point x="-23.4353" y="55.20599" /><point x="-33.91022" y="48.06738" /><point x="-44.71823" y="41.33521" /><point x="-55.15268" y="34.14709" /><point x="-66.24173" y="27.75781" /><point x="-77.38812" y="21.45782" /><point x="-89.20233" y="16.19714" /><point x="-99.34048" y="8.687012" /><point x="-110.9346" y="3.169495" /><point x="-122.1005" y="-2.996765" /><point x="-133.1597" y="-8.676575" /><point x="-144.7247" y="-14.10095" /></gesture></gestures>