<?xml version="1.0" encoding="utf-8"?><gestures><gesture name="HUMAN_5"><point x="-122.0897" y="-0.5722656" /><point x="-113.5917" y="7.684326" /><point x="-105.0937" y="15.94092" /><point x="-96.59576" y="24.19751" /><point x="-88.09784" y="32.45386" /><point x="-84.00616" y="44.77393" /><point x="-80.53711" y="57.66187" /><point x="-77.62207" y="70.77197" /><point x="-71.25336" y="81.26489" /><point x="-63.62384" y="90.80225" /><point x="-55.4248" y="99.5" /><point x="-46.92688" y="107.7563" /><point x="-38.42896" y="116.0129" /><point x="-29.82849" y="123.7747" /><point x="-19.24298" y="121.9473" /><point x="-8.743896" y="119.6201" /><point x="1.462097" y="115.5977" /><point x="11.64911" y="111.5276" /><point x="20.20673" y="103.3716" /><point x="28.99829" y="95.81982" /><point x="39.27472" y="92.10083" /><point x="49.81323" y="89.98608" /><point x="59.71173" y="85.87402" /><point x="68.53906" y="78.20044" /><point x="77.77625" y="71.37964" /><point x="87.14203" y="64.82642" /><point x="96.5578" y="58.39624" /><point x="106.147" y="52.39209" /><point x="114.9542" y="44.896" /><point x="121.2419" y="35.06372" /><point x="119.8094" y="21.55981" /><point x="117.4652" y="8.361572" /><point x="113.5081" y="-4.296143" /><point x="109.551" y="-16.95386" /><point x="106.0809" y="-29.81201" /><point x="103.488" y="-43.03149" /><point x="98.47437" y="-54.86572" /><point x="92.42963" y="-66.1001" /><point x="86.03656" y="-77.01733" /><point x="79.50763" y="-87.7937" /><point x="72.44391" y="-98.01611" /><point x="64.10504" y="-106.4905" /><point x="55.60699" y="-114.7471" /><point x="46.9931" y="-122.6453" /><point x="36.40375" y="-124.4353" /><point x="25.81445" y="-126.2253" /><point x="15.53119" y="-122.6252" /><point x="5.2547" y="-118.9063" /><point x="-4.7453" y="-114.2678" /><point x="-14.33453" y="-108.2637" /><point x="-23.77295" y="-101.8894" /><point x="-33.13867" y="-95.33594" /><point x="-42.46021" y="-88.68677" /><point x="-51.50403" y="-81.43506" /><point x="-60.54791" y="-74.18335" /><point x="-69.59186" y="-66.93164" /><point x="-78.63562" y="-59.67969" /><point x="-86.52716" y="-50.604" /><point x="-94.00336" y="-40.87085" /><point x="-100.8187" y="-30.4082" /><point x="-107.2908" y="-19.56714" /><point x="-113.7629" y="-8.726074" /><point x="-120.977" y="1.261719" /><point x="-128.7581" y="10.59814" /></gesture><gesture name="HUMAN_5"><point x="-133.6401" y="-0.3144531" /><point x="-125.4548" y="-9.116455" /><point x="-117.2695" y="-17.91821" /><point x="-109.0678" y="-26.69531" /><point x="-100.8344" y="-35.4231" /><point x="-92.60095" y="-44.15088" /><point x="-84.36743" y="-52.87866" /><point x="-75.99817" y="-61.39087" /><point x="-67.83643" y="-70.19727" /><point x="-60.33221" y="-79.94604" /><point x="-51.16577" y="-86.94287" /><point x="-41.92505" y="-93.81665" /><point x="-33.14136" y="-101.5786" /><point x="-24.57617" y="-109.7649" /><point x="-16.01099" y="-117.9514" /><point x="-6.978027" y="-125.2292" /><point x="2.262695" y="-132.1033" /><point x="12.70276" y="-134.9531" /><point x="22.86499" y="-133.4636" /><point x="32.53717" y="-127.761" /><point x="41.46594" y="-120.24" /><point x="50.39471" y="-112.7192" /><point x="59.32355" y="-105.1982" /><point x="68.25226" y="-97.67749" /><point x="77.18103" y="-90.15674" /><point x="82.31293" y="-78.37329" /><point x="87.98645" y="-66.9375" /><point x="95.22571" y="-56.86499" /><point x="101.3962" y="-45.96191" /><point x="105.0305" y="-33.0835" /><point x="109.2051" y="-20.47681" /><point x="112.8669" y="-7.692139" /><point x="114.2233" y="5.892578" /><point x="115.5793" y="19.47754" /><point x="116.3599" y="33.13232" /><point x="115.4686" y="46.66309" /><point x="112.6526" y="59.72144" /><point x="106.7855" y="71.16724" /><point x="99.76434" y="81.17383" /><point x="90.95209" y="88.81152" /><point x="80.26843" y="88.90283" /><point x="69.58472" y="88.99365" /><point x="58.92078" y="88.63062" /><point x="48.31079" y="87.02246" /><point x="37.78302" y="87.85547" /><point x="27.3208" y="90.63086" /><point x="17.77954" y="96.49658" /><point x="8.538818" y="103.3704" /><point x="-1.167114" y="108.873" /><point x="-11.39044" y="112.8513" /><point x="-21.83557" y="114.9561" /><point x="-32.51941" y="115.0469" /><point x="-42.55017" y="111.3308" /><point x="-52.21893" y="105.5042" /><point x="-61.26587" y="98.25391" /><point x="-70.19464" y="90.73267" /><point x="-79.12335" y="83.21191" /><point x="-86.83606" y="73.99097" /><point x="-93.45135" y="63.23657" /><point x="-101.6057" y="54.42896" /><point x="-109.9064" y="45.8064" /><point x="-117.9066" y="36.76221" /><point x="-125.35" y="26.93774" /><point x="-132.7935" y="17.11279" /></gesture><gesture name="HUMAN_5"><point x="-125.5111" y="0.5710449" /><point x="-116.7396" y="8.259766" /><point x="-109.431" y="17.37085" /><point x="-105.5592" y="29.82373" /><point x="-100.325" y="41.34546" /><point x="-93.96454" y="52.09778" /><point x="-88.45789" y="63.55762" /><point x="-82.95135" y="75.01758" /><point x="-77.36945" y="86.42053" /><point x="-71.7406" y="97.78784" /><point x="-64.76733" y="107.8672" /><point x="-57.37769" y="117.5475" /><point x="-49.04541" y="124.749" /><point x="-38.34583" y="125.725" /><point x="-29.43811" y="118.9788" /><point x="-20.31165" y="112.2123" /><point x="-10.18671" y="107.7974" /><point x="-0.223877" y="102.9248" /><point x="9.223877" y="96.59851" /><point x="19.44836" y="93.88013" /><point x="30.02911" y="92.27454" /><point x="40.39001" y="88.80957" /><point x="50.0097" y="83.33606" /><point x="58.87347" y="75.81323" /><point x="67.10632" y="67.37109" /><point x="74.4621" y="57.65088" /><point x="83.06116" y="49.82959" /><point x="92.19421" y="42.82349" /><point x="98.81927" y="32.49854" /><point x="106.0098" y="22.67017" /><point x="113.157" y="12.79541" /><point x="118.6283" y="1.494873" /><point x="120.851" y="-11.56836" /><point x="120.8558" y="-24.31372" /><point x="116.3048" y="-36.40601" /><point x="112.21" y="-48.72192" /><point x="108.629" y="-61.27954" /><point x="103.5461" y="-73.03882" /><point x="98.46326" y="-84.7981" /><point x="90.88184" y="-94.22803" /><point x="83.36871" y="-103.7576" /><point x="75.61902" y="-112.9189" /><point x="66.7796" y="-120.4333" /><point x="56.50482" y="-124.2751" /><point x="46.36688" y="-123.7173" /><point x="36.36157" y="-118.8984" /><point x="26.50385" y="-113.6362" /><point x="16.66791" y="-108.3057" /><point x="6.780701" y="-103.1228" /><point x="-3.075989" y="-97.86475" /><point x="-12.28314" y="-91.01074" /><point x="-21.4903" y="-84.15674" /><point x="-30.85419" y="-77.64624" /><point x="-40.302" y="-71.32007" /><point x="-49.74976" y="-64.99365" /><point x="-59.19757" y="-58.66724" /><point x="-68.39886" y="-51.85645" /><point x="-77.03284" y="-43.93042" /><point x="-86.29004" y="-37.22949" /><point x="-95.47949" y="-30.47363" /><point x="-103.0146" y="-20.96875" /><point x="-110.7089" y="-11.66577" /><point x="-119.3344" y="-4.050293" /><point x="-129.1442" y="1.355713" /></gesture></gestures>