<?xml version="1.0" encoding="utf-8"?><gestures><gesture name="HW_91"><point x="-114.4629" y="1.012573" /><point x="-111.6288" y="13.41943" /><point x="-113.6088" y="25.93066" /><point x="-111.0748" y="38.20227" /><point x="-106.4355" y="50.01434" /><point x="-100.3167" y="61.13165" /><point x="-93.0686" y="71.60065" /><point x="-85.82056" y="82.06958" /><point x="-78.57251" y="92.53857" /><point x="-71.32446" y="103.0075" /><point x="-62.69495" y="112.3448" /><point x="-51.72461" y="118.1579" /><point x="-39.20062" y="119.8328" /><point x="-26.90228" y="122.74" /><point x="-14.35883" y="124.3084" /><point x="-2.353943" y="120.8642" /><point x="9.233582" y="115.5592" /><point x="20.85748" y="110.335" /><point x="32.75098" y="105.7792" /><point x="44.78992" y="101.6057" /><point x="56.32788" y="96.19116" /><point x="66.95135" y="89.19" /><point x="77.44055" y="81.95593" /><point x="87.92969" y="74.72186" /><point x="98.41888" y="67.48785" /><point x="108.908" y="60.25366" /><point x="116.8152" y="50.49127" /><point x="122.2495" y="39.04468" /><point x="125.8248" y="26.97937" /><point x="126.8296" y="14.31982" /><point x="129.1215" y="1.80188" /><point x="126.2014" y="-10.45007" /><point x="125.2567" y="-22.98938" /><point x="124.8849" y="-35.69409" /><point x="121.903" y="-47.87427" /><point x="116.6628" y="-59.47327" /><point x="110.6755" y="-70.66614" /><point x="103.4274" y="-81.13513" /><point x="96.17938" y="-91.60413" /><point x="88.9314" y="-102.073" /><point x="78.35553" y="-108.5659" /><point x="67.34943" y="-114.9128" /><point x="55.91302" y="-120.2878" /><point x="43.75269" y="-124.1073" /><point x="31.4931" y="-125.6915" /><point x="19.12683" y="-122.594" /><point x="6.720398" y="-119.6641" /><point x="-5.30304" y="-115.5908" /><point x="-16.91571" y="-110.3414" /><point x="-28.07611" y="-104.2717" /><point x="-38.56531" y="-97.03772" /><point x="-50.00928" y="-91.52356" /><point x="-60.76678" y="-84.77295" /><point x="-71.25598" y="-77.53894" /><point x="-81.74518" y="-70.30481" /><point x="-92.23431" y="-63.0708" /><point x="-102.1279" y="-55.19055" /><point x="-110.2223" y="-45.35876" /><point x="-115.0161" y="-33.70483" /><point x="-117.6061" y="-21.26355" /><point x="-120.8785" y="-8.981079" /><point x="-120.2957" y="2.843872" /><point x="-114.7779" y="14.2926" /><point x="-111.944" y="26.69885" /></gesture><gesture name="HW_91"><point x="-114.5773" y="-0.9155273" /><point x="-116.9758" y="-13.6106" /><point x="-119.3743" y="-26.30554" /><point x="-117.6566" y="-38.13855" /><point x="-111.9203" y="-49.4491" /><point x="-108.5927" y="-61.91187" /><point x="-102.6312" y="-73.26343" /><point x="-95.56238" y="-83.79736" /><point x="-85.70563" y="-91.1355" /><point x="-75.23248" y="-97.78015" /><point x="-65.8385" y="-106.2474" /><point x="-54.35101" y="-110.949" /><point x="-42.38928" y="-114.3229" /><point x="-30.19916" y="-116.8207" /><point x="-18.00897" y="-119.3186" /><point x="-5.818787" y="-121.8164" /><point x="6.371338" y="-124.3142" /><point x="18.56152" y="-126.812" /><point x="30.75934" y="-127.3319" /><point x="42.31635" y="-123.2781" /><point x="52.63214" y="-116.0675" /><point x="62.94794" y="-108.8569" /><point x="71.59546" y="-99.63989" /><point x="80.54974" y="-90.69189" /><point x="88.02795" y="-80.47583" /><point x="93.47839" y="-68.90405" /><point x="99.1156" y="-57.39978" /><point x="106.4866" y="-47.18445" /><point x="113.8521" y="-37.15417" /><point x="117.6281" y="-24.89197" /><point x="121.8924" y="-12.98328" /><point x="127.0414" y="-1.447388" /><point x="129.4399" y="11.24756" /><point x="130.6257" y="24.03345" /><point x="129.996" y="36.9552" /><point x="126.5783" y="49.29309" /><point x="120.6566" y="60.56439" /><point x="113.0149" y="70.72461" /><point x="103.8933" y="79.43213" /><point x="93.93585" y="87.15717" /><point x="83.8313" y="94.58539" /><point x="74.98346" y="103.4117" /><point x="63.38361" y="107.9474" /><point x="51.19342" y="110.4453" /><point x="39.00323" y="112.9431" /><point x="26.81311" y="115.441" /><point x="14.62292" y="117.9388" /><point x="2.432739" y="120.4366" /><point x="-9.765991" y="122.6682" /><point x="-22.08911" y="121.0234" /><point x="-34.49475" y="120.6935" /><point x="-45.77075" y="115.806" /><point x="-57.04156" y="110.3909" /><point x="-68.35651" y="105.1201" /><point x="-78.6723" y="97.90961" /><point x="-87.50732" y="88.91809" /><point x="-94.52216" y="78.32959" /><point x="-100.4848" y="66.98187" /><point x="-106.14" y="55.46143" /><point x="-108.7986" y="42.86023" /><point x="-111.1971" y="30.16528" /><point x="-113.5956" y="17.47034" /><point x="-115.9941" y="4.775391" /><point x="-118.3925" y="-7.919189" /></gesture></gestures>