<?xml version="1.0" encoding="utf-8"?><gestures><gesture name="FOOD_31"><point x="-107.2755" y="-1.293457" /><point x="-103.7411" y="4.692322" /><point x="-100.2333" y="10.69281" /><point x="-97.05655" y="16.87585" /><point x="-93.87981" y="23.05884" /><point x="-90.70306" y="29.24188" /><point x="-87.03853" y="35.14191" /><point x="-83.2475" y="40.96857" /><point x="-79.01953" y="46.46649" /><point x="-74.47147" y="51.72351" /><point x="-69.62759" y="56.68549" /><point x="-64.38176" y="61.24652" /><point x="-59.13591" y="65.8075" /><point x="-53.89008" y="70.36853" /><point x="-48.64424" y="74.9295" /><point x="-42.57895" y="77.93115" /><point x="-35.84717" y="79.66461" /><point x="-29.11542" y="81.39813" /><point x="-22.21585" y="81.29596" /><point x="-15.28139" y="80.81171" /><point x="-8.5401" y="79.28424" /><point x="-1.89209" y="77.25305" /><point x="4.75592" y="75.22192" /><point x="11.5228" y="73.6485" /><point x="18.31911" y="72.18842" /><point x="25.1154" y="70.72833" /><point x="30.99971" y="67.24799" /><point x="36.59007" y="63.11652" /><point x="42.18044" y="58.98499" /><point x="46.79427" y="53.79639" /><point x="51.35524" y="48.55054" /><point x="55.91624" y="43.30475" /><point x="57.58308" y="36.63898" /><point x="58.94044" y="29.82141" /><point x="59.47234" y="22.95148" /><point x="58.98805" y="16.01697" /><point x="59.21892" y="9.083374" /><point x="59.52022" y="2.149841" /><point x="59.03593" y="-4.784607" /><point x="58.55165" y="-11.71912" /><point x="58.0674" y="-18.65356" /><point x="57.58315" y="-25.58801" /><point x="57.55785" y="-32.52197" /><point x="58.05916" y="-39.4552" /><point x="57.63106" y="-46.38959" /><point x="57.14677" y="-53.3241" /><point x="56.66249" y="-60.25854" /><point x="53.34669" y="-66.31238" /><point x="49.80824" y="-72.29474" /><point x="44.56242" y="-76.85577" /><point x="39.31657" y="-81.41675" /><point x="34.07074" y="-85.97778" /><point x="28.82489" y="-90.53876" /><point x="23.57904" y="-95.09979" /><point x="18.33319" y="-99.66083" /><point x="13.08734" y="-104.2218" /><point x="6.732101" y="-106.4594" /><point x="-0.1127625" y="-107.6714" /><point x="-6.776901" y="-105.9058" /><point x="-13.42491" y="-103.8746" /><point x="-20.07965" y="-101.8694" /><point x="-26.87596" y="-100.4093" /><point x="-33.67229" y="-98.94922" /><point x="-40.4686" y="-97.4892" /></gesture><gesture name="FOOD_31"><point x="-110.9158" y="1.921631" /><point x="-111.5954" y="-4.8974" /><point x="-112.2749" y="-11.71637" /><point x="-109.7038" y="-17.55341" /><point x="-105.3624" y="-22.85565" /><point x="-100.5112" y="-27.69489" /><point x="-95.65157" y="-32.52655" /><point x="-90.34218" y="-36.83942" /><point x="-84.8707" y="-40.96539" /><point x="-79.39922" y="-45.09131" /><point x="-73.92773" y="-49.21729" /><point x="-68.26259" y="-53.04449" /><point x="-62.2626" y="-56.35522" /><point x="-56.26262" y="-59.66589" /><point x="-50.26263" y="-62.97662" /><point x="-44.26265" y="-66.28735" /><point x="-38.26265" y="-69.59802" /><point x="-32.26266" y="-72.90875" /><point x="-25.80603" y="-74.81311" /><point x="-19.00562" y="-75.65869" /><point x="-12.1584" y="-75.64453" /><point x="-5.306366" y="-75.54218" /><point x="1.433868" y="-74.69043" /><point x="8.017532" y="-72.78882" /><point x="14.60118" y="-70.88721" /><point x="19.79135" y="-66.63287" /><point x="24.623" y="-61.77332" /><point x="29.45465" y="-56.9137" /><point x="34.28629" y="-52.05408" /><point x="38.66528" y="-46.85504" /><point x="41.97598" y="-40.85504" /><point x="45.28671" y="-34.8551" /><point x="48.59741" y="-28.8551" /><point x="51.90811" y="-22.8551" /><point x="55.21881" y="-16.8551" /><point x="58.52954" y="-10.8551" /><point x="61.84024" y="-4.855164" /><point x="65.15094" y="1.144836" /><point x="68.46167" y="7.144836" /><point x="71.77237" y="13.14484" /><point x="74.64679" y="19.2865" /><point x="75.49237" y="26.08691" /><point x="76.33795" y="32.88733" /><point x="77.18356" y="39.68781" /><point x="76.50171" y="46.47632" /><point x="74.16968" y="52.45013" /><point x="68.69818" y="56.57611" /><point x="63.16266" y="60.60327" /><point x="57.16266" y="63.91394" /><point x="51.16266" y="67.22467" /><point x="45.16269" y="70.5354" /><point x="39.16269" y="73.84607" /><point x="33.16272" y="77.1568" /><point x="26.7821" y="79.47168" /><point x="20.10344" y="81.00665" /><point x="13.63651" y="83.09564" /><point x="7.63652" y="86.40631" /><point x="1.227661" y="88.76471" /><point x="-5.344788" y="90.67548" /><point x="-12.08382" y="91.91895" /><point x="-18.77361" y="93.35962" /><point x="-25.30637" y="95.42932" /><point x="-32.01674" y="96.68677" /><point x="-38.81714" y="97.53235" /></gesture><gesture name="FOOD_31"><point x="-91.24731" y="-0.5374756" /><point x="-89.785" y="8.267334" /><point x="-88.32275" y="17.07214" /><point x="-86.86043" y="25.87695" /><point x="-85.08698" y="34.59491" /><point x="-81.77689" y="42.88385" /><point x="-77.5106" y="50.69604" /><point x="-72.88284" y="58.328" /><point x="-68.2551" y="65.96002" /><point x="-62.91223" y="72.45654" /><point x="-54.03001" y="73.33356" /><point x="-45.1478" y="74.21051" /><point x="-36.40771" y="72.81482" /><point x="-27.66422" y="71.0542" /><point x="-18.82637" y="69.80707" /><point x="-10.20737" y="67.68066" /><point x="-1.92038" y="64.39343" /><point x="6.099243" y="60.47565" /><point x="14.1189" y="56.55786" /><point x="21.88226" y="52.17072" /><point x="29.51422" y="47.54297" /><point x="37.14621" y="42.91522" /><point x="44.77817" y="38.28748" /><point x="52.41016" y="33.65973" /><point x="60.04211" y="29.03192" /><point x="67.67407" y="24.40417" /><point x="74.5528" y="18.96387" /><point x="79.74469" y="11.70392" /><point x="84.50375" y="4.170349" /><point x="88.83417" y="-3.634216" /><point x="92.57339" y="-11.72021" /><point x="94.71082" y="-20.25873" /><point x="95.09375" y="-29.17596" /><point x="93.83865" y="-37.94495" /><point x="91.65524" y="-46.58807" /><point x="88.61407" y="-54.97937" /><point x="84.01044" y="-62.62292" /><point x="79.38269" y="-70.25488" /><point x="74.75494" y="-77.88684" /><point x="67.18173" y="-82.39178" /><point x="58.75247" y="-84.37439" /><point x="49.84348" y="-84.14008" /><point x="41.03864" y="-82.67773" /><point x="32.15567" y="-81.84747" /><point x="23.44336" y="-80.37903" /><point x="15.23364" y="-76.87714" /><point x="7.36499" y="-72.71057" /><point x="-0.2669678" y="-68.08282" /><point x="-7.493347" y="-62.97931" /><point x="-13.27026" y="-56.1756" /><point x="-19.04718" y="-49.37189" /><point x="-23.26122" y="-41.51129" /><point x="-28.12975" y="-34.0636" /><point x="-32.7881" y="-26.54681" /><point x="-35.85677" y="-18.16547" /><point x="-40.74098" y="-10.77148" /><point x="-46.1084" y="-3.64032" /><point x="-51.72975" y="3.265381" /><point x="-58.17609" y="9.438599" /><point x="-64.64459" y="15.58673" /><point x="-71.54536" y="21.24731" /><point x="-78.71796" y="26.52399" /><point x="-86.34993" y="31.15173" /><point x="-93.9819" y="35.77948" /></gesture><gesture name="FOOD_31"><point x="-69.34471" y="0.0567627" /><point x="-65.90312" y="-7.406616" /><point x="-62.46153" y="-14.87" /><point x="-57.76797" y="-21.58051" /><point x="-52.78929" y="-28.11957" /><point x="-47.81061" y="-34.65863" /><point x="-42.1066" y="-40.46802" /><point x="-35.53798" y="-45.40765" /><point x="-28.96935" y="-50.34729" /><point x="-21.52443" y="-53.6792" /><point x="-13.99091" y="-56.87885" /><point x="-7.08046" y="-61.3277" /><point x="-0.1700134" y="-65.77649" /><point x="7.418503" y="-68.86584" /><point x="15.1295" y="-71.70966" /><point x="22.8405" y="-74.55347" /><point x="30.5515" y="-77.39728" /><point x="38.2625" y="-80.24109" /><point x="45.97353" y="-83.0849" /><point x="53.83592" y="-81.13354" /><point x="61.44957" y="-78.08972" /><point x="68.32765" y="-74.00049" /><point x="72.50502" y="-66.92255" /><point x="76.68236" y="-59.84467" /><point x="80.46175" y="-52.57782" /><point x="83.30559" y="-44.86682" /><point x="84.86903" y="-36.90637" /><point x="85.12846" y="-28.69177" /><point x="85.27519" y="-20.48865" /><point x="83.36412" y="-12.49524" /><point x="81.45302" y="-4.501831" /><point x="79.1349" y="3.350586" /><point x="75.69331" y="10.81403" /><point x="72.18712" y="18.24316" /><point x="67.94237" y="25.28082" /><point x="62.84535" y="31.59961" /><point x="56.62389" y="36.96991" /><point x="50.30754" y="42.22089" /><point x="43.67448" y="47.07367" /><point x="36.90977" y="51.73029" /><point x="29.91515" y="56.04492" /><point x="23.1241" y="60.67407" /><point x="16.33302" y="65.30316" /><point x="8.697372" y="68.29327" /><point x="0.9863739" y="71.13708" /><point x="-6.724625" y="73.9809" /><point x="-14.43564" y="76.82471" /><point x="-22.14664" y="79.66852" /><point x="-30.17043" y="81.31055" /><point x="-37.99217" y="80.44794" /><point x="-45.45554" y="77.00629" /><point x="-52.35832" y="72.82013" /><point x="-57.72861" y="66.59863" /><point x="-63.01875" y="60.31964" /><point x="-67.19609" y="53.24176" /><point x="-71.37338" y="46.16382" /><point x="-76.08694" y="39.61707" /><point x="-83.1246" y="35.37231" /><point x="-88.68925" y="29.64264" /><point x="-92.66241" y="22.48004" /><point x="-95.50623" y="14.76904" /><point x="-98.35005" y="7.058044" /><point x="-97.662" y="-0.7093506" /><point x="-95.06564" y="-8.507141" /></gesture></gestures>