<?xml version="1.0" encoding="utf-8"?><gestures><gesture name=""><point x="-2.821658" y="2.068508" /><point x="-2.91968" y="2.032864" /><point x="-3.017703" y="1.99722" /><point x="-3.117685" y="1.999311" /><point x="-3.218873" y="2.024608" /><point x="-3.317228" y="2.054908" /><point x="-3.390981" y="2.128661" /><point x="-3.464734" y="2.202413" /><point x="-3.520476" y="2.288042" /><point x="-3.559213" y="2.384884" /><point x="-3.58847" y="2.484001" /><point x="-3.597914" y="2.587875" /><point x="-3.604684" y="2.691542" /><point x="-3.579387" y="2.79273" /><point x="-3.55409" y="2.893918" /><point x="-3.518241" y="2.991363" /><point x="-3.474133" y="3.08588" /><point x="-3.430025" y="3.180397" /><point x="-3.384434" y="3.274146" /><point x="-3.332686" y="3.364705" /><point x="-3.280938" y="3.455265" /><point x="-3.22919" y="3.545824" /><point x="-3.170068" y="3.63171" /><point x="-3.110255" y="3.717158" /><point x="-3.039856" y="3.792209" /><point x="-2.955503" y="3.853557" /><point x="-2.871151" y="3.914904" /><point x="-2.778158" y="3.960361" /><point x="-2.680808" y="3.997803" /><point x="-2.583458" y="4.035245" /><point x="-2.483664" y="4.065379" /><point x="-2.383375" y="4.094032" /><point x="-2.283086" y="4.122686" /><point x="-2.179419" y="4.130941" /><point x="-2.075247" y="4.136149" /><point x="-1.971075" y="4.141358" /><point x="-1.866903" y="4.146566" /><point x="-1.762628" y="4.147624" /><point x="-1.658326" y="4.147624" /><point x="-1.554965" y="4.137186" /><point x="-1.452345" y="4.118528" /><point x="-1.352387" y="4.091885" /><point x="-1.259097" y="4.045239" /><point x="-1.166219" y="3.998134" /><point x="-1.109817" y="3.910397" /><point x="-1.053415" y="3.822661" /><point x="-0.997013" y="3.734924" /><point x="-0.9358335" y="3.650571" /><point x="-0.8717981" y="3.56824" /><point x="-0.810637" y="3.483915" /><point x="-0.7559726" y="3.395086" /><point x="-0.7013083" y="3.306256" /><point x="-0.6555845" y="3.214407" /><point x="-0.645206" y="3.110623" /><point x="-0.6379532" y="3.006824" /><point x="-0.6473964" y="2.902951" /><point x="-0.6568395" y="2.799077" /><point x="-0.7103881" y="2.710772" /><point x="-0.7682444" y="2.623987" /><point x="-0.8337975" y="2.543095" /><point x="-0.9024807" y="2.4646" /><point x="-0.9837188" y="2.401769" /><point x="-1.075285" y="2.351823" /><point x="-1.166851" y="2.301878" /></gesture></gestures>