<?xml version="1.0" encoding="utf-8"?><gestures><gesture name=""><point x="1.188066" y="1.729062" /><point x="1.100852" y="1.74152" /><point x="1.017772" y="1.735752" /><point x="0.9444684" y="1.686884" /><point x="0.8736933" y="1.634558" /><point x="0.804773" y="1.579704" /><point x="0.7292283" y="1.534377" /><point x="0.6676249" y="1.473592" /><point x="0.6108916" y="1.406472" /><point x="0.5485961" y="1.344176" /><point x="0.4929782" y="1.276088" /><point x="0.4401186" y="1.205609" /><point x="0.3872589" y="1.135129" /><point x="0.3328766" y="1.066125" /><point x="0.2640825" y="1.01109" /><point x="0.1943554" y="0.9572585" /><point x="0.1199199" y="0.9114378" /><point x="0.03782542" y="0.8798664" /><point x="-0.04959376" y="0.8689386" /><point x="-0.1370886" y="0.8592259" /><point x="-0.2251881" y="0.8592259" /><point x="-0.3132877" y="0.8592259" /><point x="-0.4013872" y="0.8592259" /><point x="-0.4894868" y="0.8592259" /><point x="-0.5775863" y="0.8592259" /><point x="-0.6656858" y="0.8592259" /><point x="-0.7537854" y="0.8592259" /><point x="-0.8403676" y="0.8745486" /><point x="-0.9181343" y="0.9126419" /><point x="-0.9914377" y="0.9615105" /><point x="-1.066808" y="1.007112" /><point x="-1.139728" y="1.056343" /><point x="-1.207637" y="1.112167" /><point x="-1.269932" y="1.174463" /><point x="-1.327789" y="1.240732" /><point x="-1.383329" y="1.309075" /><point x="-1.445625" y="1.37137" /><point x="-1.507921" y="1.433666" /><point x="-1.574671" y="1.490985" /><point x="-1.642532" y="1.547063" /><point x="-1.704828" y="1.609359" /><point x="-1.768776" y="1.669361" /><point x="-1.847575" y="1.708761" /><point x="-1.920316" y="1.757183" /><point x="-1.986617" y="1.815197" /><point x="-2.052919" y="1.873211" /><point x="-2.124204" y="1.924929" /><point x="-2.195894" y="1.976136" /><point x="-2.26896" y="2.025347" /><point x="-2.342905" y="2.07311" /><point x="-2.421704" y="2.11251" /><point x="-2.500502" y="2.151909" /><point x="-2.579301" y="2.191309" /><point x="-2.6581" y="2.230708" /><point x="-2.73771" y="2.2683" /><point x="-2.819508" y="2.301019" /><point x="-2.895217" y="2.346014" /><point x="-2.976938" y="2.375366" /><point x="-3.063327" y="2.392643" /><point x="-3.149911" y="2.407955" /><point x="-3.23801" y="2.407955" /><point x="-3.32611" y="2.407955" /><point x="-3.413652" y="2.414687" /><point x="-3.500553" y="2.429171" /></gesture></gestures>